hero_damage_component/__init__.py
hero_damage_component/example.py
hero_damage_component/frontend/build/asset-manifest.json
hero_damage_component/frontend/build/bootstrap.min.css
hero_damage_component/frontend/build/index.html
hero_damage_component/frontend/build/static/css/main.fdb5e051.css
hero_damage_component/frontend/build/static/css/main.fdb5e051.css.map
hero_damage_component/frontend/build/static/js/main.c99fd500.js
hero_damage_component/frontend/build/static/js/main.c99fd500.js.LICENSE.txt
hero_damage_component/frontend/build/static/js/main.c99fd500.js.map
dmg_chart-0.0.5.dist-info/LICENSE
dmg_chart-0.0.5.dist-info/METADATA
dmg_chart-0.0.5.dist-info/WHEEL
dmg_chart-0.0.5.dist-info/top_level.txt
dmg_chart-0.0.5.dist-info/RECORD
